brixtrx/__init__.py
brixtrx/brixtrx.py
brixtrx-0.1.0.dist-info/licenses/LICENSE
brixtrx-0.1.0.dist-info/METADATA
brixtrx-0.1.0.dist-info/WHEEL
brixtrx-0.1.0.dist-info/top_level.txt
brixtrx-0.1.0.dist-info/RECORD
