Metadata-Version: 2.4
Name: brixtrx
Version: 0.1.0
Summary: To classified transaction data whether it is transfer, withdrawal, deposit and payment/purchase
Author: Faris
Author-email: noreply@example.com
Classifier: Programming Language :: Python :: 3
Classifier: License :: OSI Approved :: MIT License
Requires-Python: >=3.6
License-File: LICENSE
Dynamic: author
Dynamic: author-email
Dynamic: classifier
Dynamic: description
Dynamic: description-content-type
Dynamic: license-file
Dynamic: requires-python
Dynamic: summary
